supertokens_flask/__init__.py
supertokens_flask/access_token.py
supertokens_flask/constants.py
supertokens_flask/cookie_and_header.py
supertokens_flask/decorators.py
supertokens_flask/default_callbacks.py
supertokens_flask/device_info.py
supertokens_flask/exceptions.py
supertokens_flask/handshake_info.py
supertokens_flask/jwt.py
supertokens_flask/process_state.py
supertokens_flask/querier.py
supertokens_flask/session.py
supertokens_flask/session_helper.py
supertokens_flask/supertokens.py
supertokens_flask/utils.py
supertokens_flask-1.4.1.dist-info/LICENSE.md
supertokens_flask-1.4.1.dist-info/METADATA
supertokens_flask-1.4.1.dist-info/WHEEL
supertokens_flask-1.4.1.dist-info/top_level.txt
supertokens_flask-1.4.1.dist-info/RECORD
