Metadata-Version: 2.1
Name: supertokens-flask
Version: 1.4.1
Summary: SuperTokens session management solution for flask
Home-page: https://github.com/supertokens/supertokens-flask
Author: SuperTokens
Author-email: team@supertokens.io
License: Apache 2.0
Platform: UNKNOWN
Classifier: Framework :: Flask
Classifier: Programming Language :: Python :: 3
Classifier: Programming Language :: Python :: 3.5
Classifier: Programming Language :: Python :: 3.6
Classifier: Programming Language :: Python :: 3.7
Classifier: Programming Language :: Python :: 3.8
Classifier: Intended Audience :: Developers
Classifier: Topic :: Internet :: WWW/HTTP :: Session
Classifier: License :: OSI Approved :: Apache Software License
Classifier: Operating System :: OS Independent
Classifier: Topic :: Software Development :: Libraries :: Python Modules
Requires-Python: >=3.7
License-File: LICENSE.md
Requires-Dist: flask
Requires-Dist: requests
Requires-Dist: pycryptodome
Provides-Extra: dev
Requires-Dist: pytest ; extra == 'dev'
Requires-Dist: flask ; extra == 'dev'
Requires-Dist: jsonschema ; extra == 'dev'
Requires-Dist: flake8 ; extra == 'dev'
Requires-Dist: autopep8 ; extra == 'dev'
Requires-Dist: pyyaml ; extra == 'dev'
Requires-Dist: flask-cors ; extra == 'dev'
